{
  "baseUrl": "https://whop.com/university-membership/?a=alexburnett21",
  "title": "TITLE IV D UNIVERSITY | Whop",
  "h1": "TITLE IV D UNIVERSITY",
  "bullets": [
    "Powered by TU TITLE IV D UNIVERSITY 5.0 ( 1 ) Contact seller Products $17.00 / month Free trial CHILD SUPPORT EDUCATION UNIVERSITY MEMBERSHIP Plus 5.0 ( 1 ) Contact seller Reviews GG Geo Goody 1 month ago Written 3 months after purchase"
  ],
  "paras": [
    "TU TITLE IV D UNIVERSITY 5.0 ( 1 ) Contact seller Products $17.00 / month Free trial CHILD SUPPORT EDUCATION UNIVERSITY MEMBERSHIP Plus 5.0 ( 1 ) Contact seller Reviews GG Geo Goody 1 month ago"
  ],
  "priceTokens": [
    "$17.00",
    "$1",
    "$1",
    "$1",
    "$21",
    "$1",
    "$1",
    "$1",
    "$1",
    "$28",
    "$1",
    "$28",
    "$28",
    "$28",
    "$28",
    "$3",
    "$3",
    "$3",
    "$10",
    "$100,000"
  ],
  "faq": [],
  "textSample": "Powered by TU TITLE IV D UNIVERSITY 5.0 ( 1 ) Contact seller Products $17.00 / month Free trial CHILD SUPPORT EDUCATION UNIVERSITY MEMBERSHIP Plus 5.0 ( 1 ) Contact seller Reviews GG Geo Goody 1 month ago Written 3 months after purchase TITLE IV D UNIVERSITY | Whop",
  "finalUrl": "https://whop.com/university-membership/?a=alexburnett21",
  "fetchedAt": "2025-11-04T22:02:15.744Z",
  "textHash": "a7716136d3f054109220f5285fde33996a6c2c0c90dbe35e8c0cfaf6b14c9689",
  "drilled": false
}